pyads_ipc_diag/__init__.py
pyads_ipc_diag/cli.py
pyads_ipc_diag/constants.py
pyads_ipc_diag/data_types.py
pyads_ipc_diag/mdp.py
pyads_ipc_diag/areas/__init__.py
pyads_ipc_diag/areas/config_area.py
pyads_ipc_diag/areas/device_area.py
pyads_ipc_diag/areas/general_area.py
pyads_ipc_diag/areas/service_area.py
pyads_ipc_diag/service/__init__.py
pyads_ipc_diag/service/cpu.py
pyads_ipc_diag/service/fan.py
pyads_ipc_diag/service/mainboard.py
pyads_ipc_diag/service/mdp_service.py
pyads_ipc_diag/service/memory.py
pyads_ipc_diag/service/nic.py
pyads_ipc_diag/service/os.py
pyads_ipc_diag/service/ras.py
pyads_ipc_diag/service/smb.py
pyads_ipc_diag/service/software.py
pyads_ipc_diag/service/time.py
pyads_ipc_diag/service/twincat.py
pyads_ipc_diag/service/users.py
pyads_ipc_diag-0.2.0.dist-info/licenses/LICENCE
pyads_ipc_diag-0.2.0.dist-info/METADATA
pyads_ipc_diag-0.2.0.dist-info/WHEEL
pyads_ipc_diag-0.2.0.dist-info/entry_points.txt
pyads_ipc_diag-0.2.0.dist-info/top_level.txt
pyads_ipc_diag-0.2.0.dist-info/RECORD
