Metadata-Version: 2.4
Name: pyads-ipc-diag
Version: 0.2.0
Summary: Read Beckhoff IPC Diagnostics via ADS using pyads
Author: Teemu Vartiainen
License: MIT
Requires-Python: >=3.9
License-File: LICENCE
Requires-Dist: pyads
Dynamic: license-file
